tdmctl/__init__.py
tdmctl/__main__.py
tdmctl/api.py
tdmctl/commands/context.py
tdmctl/commands/system/__init__.py
tdmctl/commands/system/group.py
tdmctl/core/Context.py
tdmctl/core/ContextManager.py
tdmctl/core/__init__.py
tdmctl/main.py
tdmctl-0.1.3.dist-info/entry_points.txt
tdmctl-0.1.3.dist-info/WHEEL
tdmctl-0.1.3.dist-info/METADATA
tdmctl-0.1.3.dist-info/RECORD
